wexample_filestate-0.0.74.dist-info/METADATA
wexample_filestate-0.0.74.dist-info/WHEEL
wexample_filestate-0.0.74.dist-info/entry_points.txt
wexample_filestate-0.0.74.dist-info/licenses/LICENSE
wexample_filestate/__init__.py
wexample_filestate/__pycache__/__init__.py
wexample_filestate/common/__init__.py
wexample_filestate/common/mixin/__init__.py
wexample_filestate/common/mixin/with_scope_mixin.py
wexample_filestate/config_option/__init__.py
wexample_filestate/config_option/__pycache__/__init__.py
wexample_filestate/config_option/mixin/__init__.py
wexample_filestate/config_option/mixin/__pycache__/__init__.py
wexample_filestate/config_option/mixin/item_config_option_mixin.py
wexample_filestate/config_value/__init__.py
wexample_filestate/config_value/__pycache__/__init__.py
wexample_filestate/config_value/aggregated_templates_config_value.py
wexample_filestate/config_value/content_config_value.py
wexample_filestate/config_value/file_content_config_value.py
wexample_filestate/config_value/filter/__init__.py
wexample_filestate/config_value/mode_config_value.py
wexample_filestate/config_value/name_config_value.py
wexample_filestate/config_value/readme_content_config_value.py
wexample_filestate/config_value/text_config_value.py
wexample_filestate/config_value/yaml_config_value.py
wexample_filestate/const/__init__.py
wexample_filestate/const/__pycache__/__init__.py
wexample_filestate/const/disk.py
wexample_filestate/const/filestate_markers.py
wexample_filestate/const/globals.py
wexample_filestate/const/state_items.py
wexample_filestate/const/test.py
wexample_filestate/const/types_state_items.py
wexample_filestate/enum/__init__.py
wexample_filestate/enum/__pycache__/__init__.py
wexample_filestate/enum/scopes.py
wexample_filestate/exception/__init__.py
wexample_filestate/exception/__pycache__/__init__.py
wexample_filestate/exception/abstract_file_state_exception.py
wexample_filestate/exception/bad_configuration_class_type_exception.py
wexample_filestate/exception/child_not_found_exception.py
wexample_filestate/exception/existing_shortcut_exception.py
wexample_filestate/exception/missing_env_variable_exception.py
wexample_filestate-0.0.74.dist-info/RECORD
