Metadata-Version: 2.1
Name: wexample-filestate
Version: 0.0.74
Summary: Package that allows you to manage the state of files and directories using YAML configuration files.
Author-Email: weeger <contact@wexample.com>
License: MIT
Classifier: Programming Language :: Python :: 3
Classifier: License :: OSI Approved :: MIT License
Classifier: Operating System :: OS Independent
Project-URL: homepage, https://github.com/wexample/python-filestate
Requires-Python: >=3.10
Requires-Dist: attrs>=23.1.0
Requires-Dist: cattrs>=23.1.0
Requires-Dist: jinja2
Requires-Dist: python-dotenv
Requires-Dist: tomlkit
Requires-Dist: wexample-config==0.0.97
Requires-Dist: wexample-event==0.0.79
Requires-Dist: wexample-file==0.0.52
Requires-Dist: wexample-helpers-yaml==0.0.113
Requires-Dist: wexample-prompt==0.0.97
Requires-Dist: xmltodict
Provides-Extra: dev
Requires-Dist: pytest; extra == "dev"
Requires-Dist: pytest-cov; extra == "dev"
